[{"descripcion":"Manzanas rojas, ecuatorianas","precio":"10","material":"Organico","descuento":"0","imagen":"imagenes\/04356914a75b48b0b1797427ffd756af.jpg","envases":[{"id":"1"},{"id":"2"},{"id":"4"}],"id":"1","nombre":"Manzana"},{"descripcion":"Frutillas rojas","precio":"70","material":"Organico","descuento":"0","imagen":"imagenes\/e6958040917641ca866983e409cfe622.jpg","envases":[{"id":"1"},{"id":"2"},{"id":"4"}],"id":"3","nombre":"Frutillas"},{"descripcion":"Pack x4, cepillos ecologicos de china, hechos de bambu","precio":"200","material":"Bambú, Madera, Reciclado","descuento":"0","imagen":"imagenes\/c62c4fc2e65c420996eff3b9b424c11c.jpg","envases":[{"id":"4"}],"id":"4","nombre":"Cepillo de dientes"},{"descripcion":"1kg de semillas de chia","precio":"100","material":"Organico","descuento":"0","imagen":"imagenes\/928243c75c4049348a9edfebe398301a.jpg","envases":[{"id":"1"},{"id":"2"},{"id":"4"},{"id":"6"}],"id":"5","nombre":"Semillas de chia"},{"descripcion":"Bananas ecuatorianas por kilo","precio":"80","material":"Organico","descuento":"40","imagen":"imagenes\/396964af3a46420f8eac245bbf1c3d2c.jpg","envases":[{"id":"1"},{"id":"2"}],"id":"7","nombre":"Bananas"},{"descripcion":"1 kilogramo de nutritivas semillas de lino traidas de tailandia","precio":"100","material":"Organico","descuento":"0","imagen":"imagenes\/f75eab22008a434bb812042c2820d2bd.jpg","envases":[{"id":"1"},{"id":"2"},{"id":"4"},{"id":"6"}],"id":"8","nombre":"Semillas de lino"}]